simpleicp/__init__.py
simpleicp/cli.py
simpleicp/corrpts.py
simpleicp/mathutils.py
simpleicp/optimization.py
simpleicp/pointcloud.py
simpleicp/simpleicp.py
simpleicp-2.0.15.dist-info/METADATA
simpleicp-2.0.15.dist-info/WHEEL
simpleicp-2.0.15.dist-info/top_level.txt
simpleicp-2.0.15.dist-info/RECORD
