Metadata-Version: 2.1
Name: simpleicp
Version: 2.0.15
Summary: Simple version of the Iterative Closest Point (ICP) algorithm
Home-page: https://github.com/pglira/simpleICP/tree/master/python
Author: Philipp Glira
Author-email: philipp.glira@gmail.com
License: MIT
Classifier: License :: OSI Approved :: MIT License
Classifier: Programming Language :: Python :: 3
Classifier: Programming Language :: Python :: 3.11
Requires-Dist: numpy
Requires-Dist: scipy (>=1.6)
Requires-Dist: lmfit
Requires-Dist: pandas
